lib/TOPSIS102003634.py
lib/__init__.py
TOPSIS102003634-0.0.1.dist-info/METADATA
TOPSIS102003634-0.0.1.dist-info/WHEEL
TOPSIS102003634-0.0.1.dist-info/top_level.txt
TOPSIS102003634-0.0.1.dist-info/RECORD
