Metadata-Version: 2.1
Name: TOPSIS102003634
Version: 0.0.1
Summary: Package implementing TOPSIS.
Author: Falguni Sharma
Author-email: <fsharma_be20@thapar.edu>
Keywords: python,TOPSIS
Classifier: Development Status :: 1 - Planning
Classifier: Intended Audience :: Developers
Classifier: Programming Language :: Python :: 3
Classifier: Operating System :: Unix
Classifier: Operating System :: MacOS :: MacOS X
Classifier: Operating System :: Microsoft :: Windows
